pylint_hexagonal/__about__.py
pylint_hexagonal/__init__.py
pylint_hexagonal/hexagonal_checker.py
pylint_hexagonal-0.0.1.dist-info/METADATA
pylint_hexagonal-0.0.1.dist-info/WHEEL
pylint_hexagonal-0.0.1.dist-info/licenses/LICENSE.txt
pylint_hexagonal-0.0.1.dist-info/RECORD
